smm/__init__.py
smm/example.py
smm/smm.py
smm-0.1.4.dist-info/DESCRIPTION.rst
smm-0.1.4.dist-info/METADATA
smm-0.1.4.dist-info/RECORD
smm-0.1.4.dist-info/WHEEL
smm-0.1.4.dist-info/metadata.json
smm-0.1.4.dist-info/top_level.txt
