Metadata-Version: 2.0
Name: smm
Version: 0.1.4
Summary: t-Student-Mixture-Models
Home-page: https://github.com/luiscarlosgph/t-Student-Mixture-Models
Author: Luis C. Garcia-Peraza Herrera
Author-email: luis.herrera.14@ucl.ac.uk
License: BSD 3-Clause License
Platform: UNKNOWN
Classifier: Intended Audience :: Developers
Classifier: Intended Audience :: Science/Research
Classifier: License :: OSI Approved
Classifier: Operating System :: MacOS
Classifier: Operating System :: Microsoft :: Windows
Classifier: Operating System :: POSIX
Classifier: Operating System :: Unix
Classifier: Programming Language :: C
Classifier: Programming Language :: Python
Classifier: Programming Language :: Python :: 2
Classifier: Programming Language :: Python :: 2.6
Classifier: Programming Language :: Python :: 2.7
Classifier: Programming Language :: Python :: 3
Classifier: Programming Language :: Python :: 3.3
Classifier: Programming Language :: Python :: 3.4
Classifier: Topic :: Scientific/Engineering
Classifier: Topic :: Software Development
